[
  {
    "timestamp": "2026-03-18T23:45:04Z",
    "location": "Caracas, Venezuela",
    "doc_id": "EFTA02019331",
    "text": "Epstein schedules meeting in Caracas with Francisco D'Agostino — Venezuelan financial contact"
  },
  {
    "timestamp": "2026-03-18T23:45:04Z",
    "location": "Kyiv, Ukraine",
    "doc_id": "EFTA02019404",
    "text": "Jean-Luc Brunel traces through Kiev, Kharkov, Tallinn, and Riga in early April — Eastern Europe circuit"
  },
  {
    "timestamp": "2026-03-18T23:45:04Z",
    "location": "Little St. James Island, U.S. Virgin Islands",
    "doc_id": "EFTA02019486",
    "text": "Epstein indicates plans to travel to Little St. James that evening — email confirmation"
  },
  {
    "timestamp": "2026-03-18T23:37:03Z",
    "location": "Kabul, Afghanistan",
    "doc_id": "EFTA02019028",
    "text": "Epstein emails Tom Pritzker asking about a hotel in Kabul where Pritzker was staying during vacation."
  },
  {
    "timestamp": "2026-03-18T23:37:03Z",
    "location": "Paris, France",
    "doc_id": "EFTA02019131",
    "text": "Walson waiting for Epstein in Paris Jan 8, 2012 — corroborates existing Brunel/Epstein Paris meeting."
  }
]