[
  {
    "timestamp": "2026-03-17T22:57:42Z",
    "location": "Clinton Correctional Facility, Dannemora NY",
    "doc_id": "EFTA00038275",
    "text": "FBI tip: inmate at Clinton Correctional Facility claims to possess information about Epstein death."
  },
  {
    "timestamp": "2026-03-17T22:57:42Z",
    "location": "Manchester, NH",
    "doc_id": "EFTA00038432",
    "text": "Ghislaine Maxwell sightings in Manchester, NH — local police observed her around town during investigation."
  },
  {
    "timestamp": "2026-03-17T22:53:20Z",
    "location": "Zorro Ranch, Stanley, NM",
    "doc_id": "EFTA02011179",
    "text": "Boris Nikolic flies to Epstein NM ranch Aug 18; they fly together to NYC Aug 19 to meet Bill"
  },
  {
    "timestamp": "2026-03-17T22:53:20Z",
    "location": "Virgin Gorda, British Virgin Islands",
    "doc_id": "EFTA02011128",
    "text": "Bobby Kotick & Steve Sinofsky planned Virgin Gorda trip with Epstein, Thanksgiving 2012"
  },
  {
    "timestamp": "2026-03-17T22:53:20Z",
    "location": "Core Club, 66 E 55th St, New York NY",
    "doc_id": "EFTA02011260",
    "text": "Epstein calendar: arrives NYC from LSJ Jan 2, Core Club meeting Jan 3, departs for Paris Jan 6"
  }
]