[
  {
    "timestamp": "2026-03-17T22:05:10Z",
    "location": "Program for Evolutionary Dynamics, Cambridge MA",
    "doc_id": "EFTA02010162",
    "text": "Epstein invites Noam Chomsky to meet at the Evolutionary Dynamics Institute on Brattle Street"
  },
  {
    "timestamp": "2026-03-17T22:05:10Z",
    "location": "Charles de Gaulle Airport, Paris, France",
    "doc_id": "EFTA02010012",
    "text": "Email confirms Epstein booked seat 1A on Air France CDG-JFK flight departing 1:55pm"
  },
  {
    "timestamp": "2026-03-17T22:05:10Z",
    "location": "Odessa, Ukraine",
    "doc_id": "EFTA02010128",
    "text": "Jean-Luc Brunel confirms he is in Odessa, traveling to Kiev for 2-3 days after Aug 18, 2012"
  },
  {
    "timestamp": "2026-03-17T21:57:51Z",
    "location": "Metropolitan Correctional Center (MCC New York), New York NY",
    "doc_id": "EFTA00036695",
    "text": "Email 5 days after Epstein's death: unnamed visitor toured MCC with warden — 'tour went well, the warden is impressive'"
  },
  {
    "timestamp": "2026-03-17T21:57:51Z",
    "location": "Metropolitan Correctional Center (MCC New York), New York NY",
    "doc_id": "EFTA00036668",
    "text": "Attorneys Mariel Colon and Michael Miller met MCC supervisory staff Aug 9 to negotiate Epstein's housing conditions — day before his death"
  }
]